RTL/design/modules/ir/ir.v
module ir(
    input clk,
    input rst,
    input ir_write,
    input [15:0]bus,
    output reg [15:0]ir_out
);

reg [7:0]ir_out_nxt;

////////////// flops
always @(posedge clk) begin
        if(rst)
            ir_out <= 0;
        else
            ir_out <= ir_out_nxt ;
end

///////////// comb
always @(*) begin
    if(ir_write)
        ir_out_nxt = bus[15:0];
    else
        ir_out_nxt = ir_out ;
end


endmodule

RTL/design/modules/ir/ir_tb.v
`timescale 1ns/1ps

module tb;

reg [15:0]bus; 
reg clk,rst,ir_write;
wire [15:0]ir_out;

ir dut(
    .clk(clk),
    .rst(rst),
    .ir_write(ir_write),
    .bus(bus),
    .ir_out(ir_out)
);

always #5 clk = ~clk ; 

initial begin
    {clk,rst,ir_write,bus} = 0 ;
    $dumpfile("output.vcd");
    $dumpvars(0,tb);
    #100 $finish ; 

end

initial begin

#12;
rst  = 1;

#8 ;
rst = 0;

#1;
bus = 16'd74;

#2;
ir_write = 1;

#5;
ir_write = 0;


end
 
endmodule

RTL/design/modules/ir/output.vcd
$date
	Fri Sep 26 21:50:48 2025
$end
$version
	Icarus Verilog
$end
$timescale
	1ps
$end
$scope module tb $end
$var wire 16 ! ir_out [15:0] $end
$var reg 16 " bus [15:0] $end
$var reg 1 # clk $end
$var reg 1 $ ir_write $end
$var reg 1 % rst $end
$scope module dut $end
$var wire 16 & bus [15:0] $end
$var wire 1 # clk $end
$var wire 1 $ ir_write $end
$var wire 1 % rst $end
$var reg 16 ' ir_out [15:0] $end
$var reg 8 ( ir_out_nxt [7:0] $end
$upscope $end
$upscope $end
$enddefinitions $end
$comment Show the parameter values. $end
$dumpall
$end
#0
$dumpvars
bx (
bx '
b0 &
0%
0$
0#
b0 "
bx !
$end
#5000
b0xxxxxxxx !
b0xxxxxxxx '
1#
#10000
0#
#12000
1%
#15000
b0 (
b0 !
b0 '
1#
#20000
0#
0%
#21000
b1001010 "
b1001010 &
#23000
b1001010 (
1$
#25000
b1001010 !
b1001010 '
1#
#28000
0$
