RTL/design/modules/pc/pc.v
module pc(
    input clk,
    input rst,
    input pc_inc,
    input pc_write,
    input [15:0]bus,
    output reg [15:0]pc_out
);

reg [15:0]pc_out_nxt;


////////////// flops
always @(posedge clk ) begin
        if(rst)
            pc_out <= 0;
        else
            pc_out <= pc_out_nxt; 
end

///////////// comb
always @(*) begin
    if(pc_write)
        pc_out_nxt = bus;
    else if(pc_inc)
        pc_out_nxt = pc_out + 1 ;
    else
        pc_out_nxt = pc_out;
end


endmodule

RTL/design/modules/pc/pc_tb.v
`timescale 1ns/1ps

module tb;

    reg clk;
    reg rst;
    reg pc_write;
    reg pc_inc;
    reg [15:0]bus;
    wire [15:0]pc_out;


    pc dut(
        .clk(clk),
        .rst(rst),
        .pc_inc(pc_inc),
        .pc_write(pc_write),
        .bus(bus),
        .pc_out(pc_out)
    );

always #5 clk = ~clk ; 

initial
begin
    {clk,rst,pc_write,bus,pc_inc} = 0 ;
    $dumpfile("output.vcd");
    $dumpvars(0,tb);
    #200 $finish ;

end


initial begin

    #2;
    rst <= 1;

    #5;
    rst <= 0 ;

    #2;
    bus <= 4'b0101;

    #3;
    pc_write <= 1;

    #5;
    pc_write <= 0;

    #2;
    pc_inc <= 1 ;

    #20;
    pc_inc <= 0 ;

end


endmodule

RTL/design/modules/pc/output.vcd
$date
	Fri Sep 26 18:59:15 2025
$end
$version
	Icarus Verilog
$end
$timescale
	1ps
$end
$scope module tb $end
$var wire 16 ! pc_out [15:0] $end
$var reg 16 " bus [15:0] $end
$var reg 1 # clk $end
$var reg 1 $ pc_inc $end
$var reg 1 % pc_write $end
$var reg 1 & rst $end
$scope module dut $end
$var wire 16 ' bus [15:0] $end
$var wire 1 # clk $end
$var wire 1 $ pc_inc $end
$var wire 1 % pc_write $end
$var wire 1 & rst $end
$var reg 16 ( pc_out [15:0] $end
$var reg 16 ) pc_out_nxt [15:0] $end
$upscope $end
$upscope $end
$enddefinitions $end
$comment Show the parameter values. $end
$dumpall
$end
#0
$dumpvars
bx )
bx (
b0 '
0&
0%
0$
0#
b0 "
bx !
$end
#2000
1&
#5000
b0 )
b0 !
b0 (
1#
#7000
0&
#9000
b101 "
b101 '
#10000
0#
#12000
b101 )
1%
#15000
b101 !
b101 (
1#
#17000
0%
#19000
b110 )
1$
#20000
0#
#25000
b111 )
b110 !
b110 (
1#
#30000
0#
#35000
b1000 )
b111 !
b111 (
1#
#39000
b111 )
0$
