RTL/design/modules/alu/alu.v
`define ADD 4'd0
`define SUB 4'd1
`define INC 4'd2
`define DEC 4'd3
`define AND 4'd4
`define OR 4'd5
`define XOR 4'd6
`define NOT 4'd7

module alu(
    input signed [15:0]a,
    input signed [15:0]b,
    input [3:0]op,
    output reg signed[16:0]res
);

    always@(*) begin
        case(op)
        `ADD: res = a + b ;
        `SUB: res = a - b ;
        `INC: res = a + $signed(1);
        `DEC: res = a - $signed(1);
        `AND: res = {1'b0, a & b};
        `OR:  res = {1'b0, a | b};
        `XOR: res = {1'b0, a ^ b};
        `NOT: res = {1'b0, ~a};
        default: res = 17'd0;
        endcase

    end
    
endmodule

RTL/design/modules/alu/alu_tb.v
`timescale 1ns/1ps

module tb;

reg signed [15:0]a,b;
reg [3:0]op;
wire [16:0]res;

alu dut(
    .a(a),
    .b(b),
    .op(op),
    .res(res)
);


integer i;

initial begin
    for(i = 0 ; i <= 10 ; i ++) begin

        a = $random%10;
        b = $random%10;
        op = $urandom%8;
        #5;

    end

end

initial begin
    {a,b,op} = 0;
    $dumpfile("output.vcd");
    $dumpvars(0,tb);
    #100 $finish ; 

end


endmodule

RTL/design/modules/alu/output.vcd
$date
	Sat Sep 27 01:58:04 2025
$end
$version
	Icarus Verilog
$end
$timescale
	1ps
$end
$scope module tb $end
$var wire 17 ! res [16:0] $end
$var reg 16 " a [15:0] $end
$var reg 16 # b [15:0] $end
$var reg 4 $ op [3:0] $end
$var integer 32 % i [31:0] $end
$scope module dut $end
$var wire 16 & a [15:0] $end
$var wire 16 ' b [15:0] $end
$var wire 4 ( op [3:0] $end
$var reg 17 ) res [16:0] $end
$upscope $end
$upscope $end
$enddefinitions $end
$comment Show the parameter values. $end
$dumpall
$end
#0
$dumpvars
b0 )
b0 (
b0 '
b0 &
b0 %
b0 $
b0 #
b0 "
b0 !
$end
#5000
b1 $
b1 (
b1111111111110111 #
b1111111111110111 '
b1111111111110111 "
b1111111111110111 &
b1 %
#10000
b111 #
b111 '
b111 "
b111 &
b10 %
#15000
b11111111111111110 !
b11111111111111110 )
b11 $
b11 (
b1111111111111100 #
b1111111111111100 '
b1111111111111111 "
b1111111111111111 &
b11 %
#20000
b1001 !
b1001 )
b101 $
b101 (
b1001 #
b1001 '
b1 "
b1 &
b100 %
#25000
b1111 !
b1111 )
b111 #
b111 '
b1000 "
b1000 &
b101 %
#30000
b1011 !
b1011 )
b10 #
b10 '
b1001 "
b1001 &
b110 %
#35000
b1010 !
b1010 )
b10 $
b10 (
b0 #
b0 '
b111 %
#40000
b11111111111111011 !
b11111111111111011 )
b1 $
b1 (
b1111111111111100 #
b1111111111111100 '
b1111111111110111 "
b1111111111110111 &
b1000 %
#45000
b1111111111111111 !
b1111111111111111 )
b101 $
b101 (
b1111111111111111 #
b1111111111111111 '
b101 "
b101 &
b1001 %
#50000
b1111111111110111 !
b1111111111110111 )
b110 $
b110 (
b1001 #
b1001 '
b1111111111111110 "
b1111111111111110 &
b1010 %
#55000
b1011 %
