RTL/design/modules/sap/ram.v

module ram(
    input clk,
    input ram_write,
    input [15:0]bus,
    input [15:0]addr,
    output  [15:0]ram_out
);

reg [15:0]mem[255:0];

always @(posedge clk) begin
        if(ram_write) // Synchronous Write
            mem[addr] <= bus;

        
end

assign ram_out = mem[addr]; // Combinational Read


endmodule

RTL/design/modules/pc/pc.v
module pc(
    input clk,
    input rst,
    input pc_inc,
    input pc_write,
    input [15:0]bus,
    output reg [15:0]pc_out
);

reg [15:0]pc_out_nxt;


////////////// flops
always @(posedge clk ) begin
        if(rst)
            pc_out <= 16'd10;
        else
            pc_out <= pc_out_nxt; 
end

///////////// comb
always @(*) begin
    if(pc_write)
        pc_out_nxt = {8'b0,bus[7:0]};
    else if(pc_inc)
        pc_out_nxt = pc_out + 1 ;
    else
        pc_out_nxt = pc_out;
end


endmodule

RTL/design/modules/output/out.v
module out(
    input clk,
    input rst,
    input [15:0]bus,
    input out_write,
    output reg[15:0]_out_
);

    reg [15:0] _out_nxt;

////////////// flops
always @(posedge clk) begin
        if(rst)
            _out_ <= 0;
        else
            _out_ <= _out_nxt ;
end

///////////// comb
always @(*) begin
    if(out_write)
        _out_nxt = bus;
    else
        _out_nxt = _out_ ;
end



endmodule

RTL/design/modules/mar/mar.v
module mar(
    input clk,
    input rst,
    input mar_write,
    input [15:0]bus,
    output reg [15:0]mar_out
);

reg [15:0]mar_out_nxt;


////////////// flops
always @(posedge clk) begin
        if(rst)
            mar_out <= 0;
        else
            mar_out <= mar_out_nxt ;
end

///////////// comb
always @(*) begin
    if(mar_write)
        mar_out_nxt = bus;
    else
        mar_out_nxt = mar_out ;
end


endmodule

RTL/design/modules/ir/ir.v
module ir(
    input clk,
    input rst,
    input ir_write,
    input [15:0]bus,
    output reg [15:0]ir_out
);

reg [15:0]ir_out_nxt;

////////////// flops
always @(posedge clk) begin
        if(rst)
            ir_out <= 0;
        else
            ir_out <= ir_out_nxt ;
end

///////////// comb
always @(*) begin
    if(ir_write)
        ir_out_nxt = bus;
    else
        ir_out_nxt = ir_out ;
end


endmodule

RTL/design/modules/sap/flag.v
module flag(
    input clk,
    input rst,
    input flag_write,
    input [1:0]flag_in,
    output reg [1:0]flag_out
);

reg [1:0]flag_out_nxt;

////////////// flops
always @(posedge clk) begin
        if(rst)
            flag_out <= 0;
        else
            flag_out <= flag_out_nxt ;
end

///////////// comb
always @(*) begin
    if(flag_write)
        flag_out_nxt = flag_in ;
    else
        flag_out_nxt = flag_out ;
end


endmodule

RTL/design/modules/sap/cu.v
`define LDA 8'd0
`define STA 8'd1
`define ADD 8'd2
`define SUB 8'd3
`define INCA 8'd4
`define DECR 8'd5
`define JMPZ 8'd6
`define JMPC 8'd7
`define JMP  8'd8
`define NOP 8'd9
`define LDI 8'd10
`define OUT 8'd11
`define HLT 8'd12
`define AND 8'd13
`define OR  8'd14
`define XOR 8'd15
`define NOT 8'd16


`define ADD_OP 4'd0
`define SUB_OP 4'd1
`define INC_OP 4'd2
`define DEC_OP 4'd3
`define AND_OP 4'd4
`define OR_OP 4'd5
`define XOR_OP 4'd6
`define NOT_OP 4'd7


module cu(
    input clk,
    input rst,
    input [1:0]flag,   // flag[0] = Zero Flag , flag[1] = Carry Flag
    input [7:0]opcode,
    output [13:0]cs,
    output [4:0]bus_cs
);

localparam [3:0] 
    idle = 0,

    fetch1 = 1,
    fetch2 = 2,

    lda1 = 3,
    lda2 = 4,

    sta1 = 5,
    sta2 = 6,

    alu1 = 7,
    alu2 = 8,
    alu3 = 9,

    jmp1 = 10,

    ldi1 = 11,
    
    out1 = 12,

    hlt = 13;


reg [3:0]state,state_nxt;


////////////////////////////////
// Control Signals 
reg acc_write;
reg acc_lower_write;
reg [3:0]alu_op;
reg b_write;
reg flag_write;
reg ir_write;
reg mar_write;
reg out_write;
reg pc_inc;
reg pc_write;
reg ram_write;

assign cs = {
                acc_write,
                acc_lower_write,
                alu_op,
                b_write,
                flag_write, 
                ir_write,
                mar_write,
                out_write,
                pc_inc,
                pc_write,
                ram_write
                
                };

////////////////////////////////////
// Bus Control signals

reg acc_to_bus;
reg alu_to_bus;
reg ir_to_bus;
reg pc_to_bus;
reg ram_to_bus;

assign bus_cs = {

                acc_to_bus,
                alu_to_bus,
                ir_to_bus,
                pc_to_bus,
                ram_to_bus

                };

//////////// flops
always @(negedge  clk ) begin

    if(rst) state <= idle;
    else    state <= state_nxt;
    
end

/////////// Nxt State logic
always @(*) begin

    state_nxt = idle ;

    case(state)

        //////// Idle
        idle : state_nxt = fetch1 ;

        //////// fetch & decode
        fetch1 : state_nxt = fetch2 ;

        fetch2 : begin
            state_nxt = fetch1;
            case(opcode)
                `LDA : state_nxt = lda1 ;
                `STA : state_nxt = sta1 ;
                `ADD,`SUB,`INCA,`DECR,`AND,`OR,`XOR,`NOT : state_nxt = alu1 ;
                `JMP: state_nxt = jmp1;
                `JMPZ: state_nxt = flag[0]? jmp1 : fetch1;
                `JMPC  : state_nxt = flag[1]? jmp1 : fetch1;
                `NOP :  state_nxt = fetch1 ;
                `LDI :  state_nxt = ldi1 ;
                `OUT :  state_nxt = out1 ;
                `HLT :  state_nxt = hlt ;
                
            endcase


        end

        /////////////////// Load

        lda1 : state_nxt = lda2 ;
        lda2 : state_nxt = fetch1 ;

        ///////////////// Store
        sta1 : state_nxt = sta2 ;
        sta2 : state_nxt = fetch1 ;

        ///////////////// ALU
        alu1 : begin
               state_nxt = fetch1;
                case(opcode)
                    `ADD,`SUB,`AND,`OR,`XOR: state_nxt = alu2;
                    `INCA,`DECR,`NOT : state_nxt = fetch1;
                endcase
                end
        alu2 : begin
            state_nxt = alu3;
        end
        
        alu3 : state_nxt = fetch1 ;


        ////////////////// Jump if Zero
        jmp1 : begin
            state_nxt = fetch1;
        end

        ///////////////////// Load Immediate
        ldi1 : state_nxt = fetch1 ;

        ///////////////////// Output Register
        out1 : state_nxt = fetch1 ;

        ///////////////////////  Halt
        hlt : state_nxt = hlt ;

    endcase
    
end




always @(*) begin

    // Control Signals
    acc_write = 0;
    acc_lower_write = 0;
    alu_op = 0;
    b_write = 0;
    flag_write = 0;
    ir_write = 0;
    mar_write = 0;
    out_write = 0;
    pc_inc = 0;
    pc_write = 0;
    ram_write = 0;

    // Bus Control Signals
    acc_to_bus = 0;
    alu_to_bus = 0;
    ir_to_bus = 0;
    pc_to_bus = 0;
    ram_to_bus = 0;

    

    case(state)
        fetch1 : begin
            mar_write = 1'b1;
            pc_to_bus = 1'b1;
        end

        fetch2 : begin
            ir_write = 1'b1;
            pc_inc = 1'b1;
            ram_to_bus = 1'b1;
        end

        lda1 : begin
            mar_write = 1'b1;
            ir_to_bus = 1'b1;
        end

        lda2 : begin
            acc_write = 1'b1;
            ram_to_bus = 1'b1;
        end

        sta1 : begin
            mar_write = 1'b1;
            ir_to_bus = 1'b1;
        end

        sta2 : begin
            ram_write = 1'b1;
            acc_to_bus = 1'b1;
        end

        alu1: begin
            case(opcode) 

            `INCA: begin
                alu_op = `INC_OP;
                flag_write = 1'b1;
                acc_write = 1'b1;
                alu_to_bus = 1'b1;
            end
            `DECR : begin
                alu_op = `DEC_OP;
                flag_write = 1'b1;
                acc_write = 1'b1;
                alu_to_bus = 1'b1;
            end
            `NOT : begin
                alu_op = `NOT_OP;
                flag_write = 1'b1;
                acc_write = 1'b1;
                alu_to_bus = 1'b1;
            end

            `ADD,`SUB,`AND,`OR,`XOR : begin
                mar_write = 1'b1;
                ir_to_bus = 1'b1;  
            end
                
            endcase
        end

        alu2 : begin
            case(opcode)

            `ADD,`SUB,`AND,`OR,`XOR : begin

                ram_to_bus = 1'b1;
                b_write = 1'b1;
                
            end
            
            endcase
        end

        alu3 : begin
            acc_write = 1'b1;
            alu_to_bus = 1'b1;
            flag_write = 1'b1;
            case(opcode)
                `ADD : alu_op = `ADD_OP;
                `SUB : alu_op = `SUB_OP;
                `AND : alu_op = `AND_OP;
                `OR  : alu_op = `OR_OP ;
                `XOR : alu_op = `XOR_OP;

            endcase

        end

        jmp1 : begin

            pc_write = 1'b1;
            ir_to_bus = 1'b1;

        end

        ldi1 : begin

            acc_lower_write = 1'b1;
            ir_to_bus = 1'b1;

        end

        out1 : begin

            out_write = 1'b1;
            acc_to_bus = 1'b1;

        end


    endcase

    
end


endmodule

RTL/design/modules/sap/b_register.v
module b_register(
    input clk,
    input rst,
    input b_write,
    input [15:0]bus,
    output reg [15:0]bout
);

reg [15:0]bout_nxt;


////////////// flops
always @(posedge clk ) begin
        if(rst)
            bout <= 0;
        else
            bout <= bout_nxt ;
end

///////////// comb
always @(*) begin
    if(b_write)
        bout_nxt = bus;
    else
        bout_nxt = bout ;
end


endmodule

RTL/design/modules/alu/alu.v
`define ADD_OP 4'd0
`define SUB_OP 4'd1
`define INC_OP 4'd2
`define DEC_OP 4'd3
`define AND_OP 4'd4
`define OR_OP 4'd5
`define XOR_OP 4'd6
`define NOT_OP 4'd7

module alu(
    input signed [15:0]a,
    input signed [15:0]b,
    input [3:0]op,
    output reg signed[15:0]alu_out,
    output reg [1:0]flag
);

    reg [16:0]res;
    always@(*) begin
        case(op)
        `ADD_OP: res = a + b ;
        `SUB_OP: res = a - b ;
        `INC_OP: res = a + $signed(1);
        `DEC_OP: res = a - $signed(1);
        `AND_OP: res = {1'b0, a & b};
        `OR_OP:  res = {1'b0, a | b};
        `XOR_OP: res = {1'b0, a ^ b};
        `NOT_OP: res = {1'b0, ~a};
        default: res = 17'd0;
        endcase

    end


    always @(*) begin
        flag[0] = ~|res[15:0]; // Zero Flag
        flag[1] = res[16]    ; // Overflow flag
        alu_out = res[15:0];
    end
    
endmodule

RTL/design/modules/accumulator/accumulator.v
module accumulator(
    input clk,
    input rst,
    input acc_write,
    input acc_lower_write,
    input [15:0]bus,
    output reg [15:0]aout
);

reg [15:0]aout_nxt;


////////////// flops
always @(posedge clk ) begin
        if(rst)
            aout <= 0;
        else
            aout <= aout_nxt ;
end

///////////// comb
always @(*) begin
    if(acc_write)
        aout_nxt = bus;
    else if(acc_lower_write)
        aout_nxt = {8'b0,bus[7:0]};
    else
        aout_nxt = aout ;
end


endmodule

RTL/design/modules/sap/sap.v
`include "accumulator.v"
`include "alu.v"
`include "b_register.v"
`include "cu.v"
`include "flag.v"
`include "ir.v"
`include "mar.v"
`include "out.v"
`include "pc.v"
`include "ram.v"




module sap(
    input clk,rst,
    output [15:0]debug
);

reg [15:0]bus;


// Accumulator
wire acc_write,acc_lower_write;
wire [15:0]aout;

// ALU
wire [15:0]bout;
wire [3:0]alu_op;
wire [15:0]alu_out;
wire [1:0]flag;

// B-Register
wire b_write;

// Control Unit
wire [7:0]opcode;
wire [13:0]cs;
wire [4:0]bus_cs;

// Flags
wire flag_write;
wire [1:0]flag_out;

// IR
wire ir_write;
wire [15:0]ir_out;

// MAR
wire mar_write;
wire [15:0]mar_out;

//out
wire out_write;
wire [15:0]_out_;

// PC
wire pc_inc;
wire pc_write;
wire [15:0]pc_out;

// RAM
wire ram_write;
wire [15:0]ram_out;

// Bus Control signals

wire acc_to_bus;
wire alu_to_bus;
wire ir_to_bus;
wire pc_to_bus;
wire ram_to_bus;


///// Opcode

assign opcode = ir_out[15:8];


////// Debug Bus
assign debug = bus;

//////// Instrantiation


accumulator accumulator1(
    .clk(clk),
    .rst(rst),
    .acc_write(acc_write),
    .acc_lower_write(acc_lower_write),
    .bus(bus),
    .aout(aout)
);

alu alu1(
    .a(aout),
    .b(bout),
    .op(alu_op),
    .alu_out(alu_out),
    .flag(flag)

);

b_register b_register1(
    .clk(clk),
    .rst(rst),
    .b_write(b_write),
    .bus(bus),
    .bout(bout)
);

cu cu1(
    .clk(clk),
    .rst(rst),
    .flag(flag_out),
    .opcode(opcode),
    .cs(cs),
    .bus_cs(bus_cs)
);

flag flag1(
    .clk(clk),
    .rst(rst),
    .flag_write(flag_write),
    .flag_in(flag),
    .flag_out(flag_out)
);

ir ir1(
    .clk(clk),
    .rst(rst),
    .ir_write(ir_write),
    .bus(bus),
    .ir_out(ir_out)
);

mar mar1(
    .clk(clk),
    .rst(rst),
    .mar_write(mar_write),
    .bus(bus),
    .mar_out(mar_out)
);

out out1(
    .clk(clk),
    .rst(rst),
    .bus(bus),
    .out_write(out_write),
    ._out_(_out_)
);

pc pc1(
    .clk(clk),
    .rst(rst),
    .pc_inc(pc_inc),
    .pc_write(pc_write),
    .bus(bus),
    .pc_out(pc_out)
);

ram ram1(
    .clk(clk),
    .ram_write(ram_write),
    .bus(bus),
    .addr(mar_out),
    .ram_out(ram_out)
);


///////////////// Control Signals

assign {acc_write,acc_lower_write,alu_op,b_write,flag_write, ir_write,mar_write,out_write,pc_inc,pc_write,ram_write} = cs;
assign {acc_to_bus,alu_to_bus,ir_to_bus,pc_to_bus,ram_to_bus} = bus_cs;


////////////// Bus Arbitration Logic
always @(*) begin

    bus = 16'd0;

    case(1'b1)

        acc_to_bus : bus = aout ;
        alu_to_bus : bus = alu_out;
        ir_to_bus  : bus = {8'd0,ir_out[7:0]};
        pc_to_bus : bus = pc_out;
        ram_to_bus : bus = ram_out;


    endcase
    
end




endmodule

RTL/design/modules/sap/tb.v
`timescale 1ns/1ps
module tb;

reg clk,rst;
wire [15:0]debug;

integer i ;

always #1 clk = ~clk ;

sap dut(
    .rst(rst),
    .clk(clk),
    .debug(debug)
);

initial begin

    $dumpfile("sim_output.vcd");
    $dumpvars(0,tb);
    #1000;
    $finish;

end

initial begin // Writing Instr and Data to RAM for simulation

    for(i =0 ; i <256; i ++)
        dut.ram1.mem[i] = 0;

    /// Data Section
    dut.ram1.mem[0] = 16'h0000;
    dut.ram1.mem[1] = 16'h0001;

    // Instr Section
    dut.ram1.mem[10] = 16'h0000;
    dut.ram1.mem[11] = 16'h0B00;
    dut.ram1.mem[12] = 16'h0201;
    dut.ram1.mem[13] = 16'h0102;
    dut.ram1.mem[14] = 16'h0001;
    dut.ram1.mem[15] = 16'h0100;
    dut.ram1.mem[16] = 16'h0002;
    dut.ram1.mem[17] = 16'h0101;
    dut.ram1.mem[18] = 16'h080A;

end

initial begin
    clk = 0;
    rst = 1;
    #11;
    rst = 0;

end



endmodule

RTL/design/modules/sap/sim_output.vcd
$date
	Fri Oct 10 12:11:18 2025
$end
$version
	Icarus Verilog
$end
$timescale
	1ps
$end
$scope module tb $end
$var wire 16 ! debug [15:0] $end
$var reg 1 " clk $end
$var reg 1 # rst $end
$var integer 32 $ i [31:0] $end
$scope module dut $end
$var wire 1 " clk $end
$var wire 16 % debug [15:0] $end
$var wire 1 # rst $end
$var wire 1 & ram_write $end
$var wire 1 ' ram_to_bus $end
$var wire 16 ( ram_out [15:0] $end
$var wire 1 ) pc_write $end
$var wire 1 * pc_to_bus $end
$var wire 16 + pc_out [15:0] $end
$var wire 1 , pc_inc $end
$var wire 1 - out_write $end
$var wire 8 . opcode [7:0] $end
$var wire 1 / mar_write $end
$var wire 16 0 mar_out [15:0] $end
$var wire 1 1 ir_write $end
$var wire 1 2 ir_to_bus $end
$var wire 16 3 ir_out [15:0] $end
$var wire 1 4 flag_write $end
$var wire 2 5 flag_out [1:0] $end
$var wire 2 6 flag [1:0] $end
$var wire 14 7 cs [13:0] $end
$var wire 5 8 bus_cs [4:0] $end
$var wire 16 9 bout [15:0] $end
$var wire 1 : b_write $end
$var wire 16 ; aout [15:0] $end
$var wire 1 < alu_to_bus $end
$var wire 16 = alu_out [15:0] $end
$var wire 4 > alu_op [3:0] $end
$var wire 1 ? acc_write $end
$var wire 1 @ acc_to_bus $end
$var wire 1 A acc_lower_write $end
$var wire 16 B _out_ [15:0] $end
$var reg 16 C bus [15:0] $end
$scope module accumulator1 $end
$var wire 1 A acc_lower_write $end
$var wire 1 ? acc_write $end
$var wire 16 D bus [15:0] $end
$var wire 1 " clk $end
$var wire 1 # rst $end
$var reg 16 E aout [15:0] $end
$var reg 16 F aout_nxt [15:0] $end
$upscope $end
$scope module alu1 $end
$var wire 16 G a [15:0] $end
$var wire 4 H op [3:0] $end
$var wire 16 I b [15:0] $end
$var reg 16 J alu_out [15:0] $end
$var reg 2 K flag [1:0] $end
$var reg 17 L res [16:0] $end
$upscope $end
$scope module b_register1 $end
$var wire 1 : b_write $end
$var wire 16 M bus [15:0] $end
$var wire 1 " clk $end
$var wire 1 # rst $end
$var reg 16 N bout [15:0] $end
$var reg 16 O bout_nxt [15:0] $end
$upscope $end
$scope module cu1 $end
$var wire 1 " clk $end
$var wire 8 P opcode [7:0] $end
$var wire 1 # rst $end
$var wire 2 Q flag [1:0] $end
$var wire 14 R cs [13:0] $end
$var wire 5 S bus_cs [4:0] $end
$var parameter 4 T alu1 $end
$var parameter 4 U alu2 $end
$var parameter 4 V alu3 $end
$var parameter 4 W fetch1 $end
$var parameter 4 X fetch2 $end
$var parameter 4 Y hlt $end
$var parameter 4 Z idle $end
$var parameter 4 [ jmp1 $end
$var parameter 4 \ lda1 $end
$var parameter 4 ] lda2 $end
$var parameter 4 ^ ldi1 $end
$var parameter 4 _ out1 $end
$var parameter 4 ` sta1 $end
$var parameter 4 a sta2 $end
$var reg 1 b acc_lower_write $end
$var reg 1 c acc_to_bus $end
$var reg 1 d acc_write $end
$var reg 4 e alu_op [3:0] $end
$var reg 1 f alu_to_bus $end
$var reg 1 g b_write $end
$var reg 1 h flag_write $end
$var reg 1 i ir_to_bus $end
$var reg 1 j ir_write $end
$var reg 1 k mar_write $end
$var reg 1 l out_write $end
$var reg 1 m pc_inc $end
$var reg 1 n pc_to_bus $end
$var reg 1 o pc_write $end
$var reg 1 p ram_to_bus $end
$var reg 1 q ram_write $end
$var reg 4 r state [3:0] $end
$var reg 4 s state_nxt [3:0] $end
$upscope $end
$scope module flag1 $end
$var wire 1 " clk $end
$var wire 2 t flag_in [1:0] $end
$var wire 1 4 flag_write $end
$var wire 1 # rst $end
$var reg 2 u flag_out [1:0] $end
$var reg 2 v flag_out_nxt [1:0] $end
$upscope $end
$scope module ir1 $end
$var wire 16 w bus [15:0] $end
$var wire 1 " clk $end
$var wire 1 1 ir_write $end
$var wire 1 # rst $end
$var reg 16 x ir_out [15:0] $end
$var reg 16 y ir_out_nxt [15:0] $end
$upscope $end
$scope module mar1 $end
$var wire 16 z bus [15:0] $end
$var wire 1 " clk $end
$var wire 1 / mar_write $end
$var wire 1 # rst $end
$var reg 16 { mar_out [15:0] $end
$var reg 16 | mar_out_nxt [15:0] $end
$upscope $end
$scope module out1 $end
$var wire 16 } bus [15:0] $end
$var wire 1 " clk $end
$var wire 1 - out_write $end
$var wire 1 # rst $end
$var reg 16 ~ _out_ [15:0] $end
$var reg 16 !" _out_nxt [15:0] $end
$upscope $end
$scope module pc1 $end
$var wire 16 "" bus [15:0] $end
$var wire 1 " clk $end
$var wire 1 , pc_inc $end
$var wire 1 ) pc_write $end
$var wire 1 # rst $end
$var reg 16 #" pc_out [15:0] $end
$var reg 16 $" pc_out_nxt [15:0] $end
$upscope $end
$scope module ram1 $end
$var wire 16 %" addr [15:0] $end
$var wire 16 &" bus [15:0] $end
$var wire 1 " clk $end
$var wire 16 '" ram_out [15:0] $end
$var wire 1 & ram_write $end
$upscope $end
$upscope $end
$upscope $end
$enddefinitions $end
$comment Show the parameter values. $end
$dumpall
b110 a
b101 `
b1100 _
b1011 ^
b100 ]
b11 \
b1010 [
b0 Z
b1101 Y
b10 X
b1 W
b1001 V
b1000 U
b111 T
$end
#0
$dumpvars
bx '"
b0 &"
bx %"
bx $"
bx #"
b0 ""
bx !"
bx ~
b0 }
bx |
bx {
b0 z
bx y
bx x
b0 w
bx v
bx u
bx t
b1 s
b0 r
0q
0p
0o
0n
0m
0l
0k
0j
0i
0h
0g
0f
b0 e
0d
0c
0b
b0 S
b0 R
bx Q
bx P
bx O
bx N
b0 M
bx L
bx K
bx J
bx I
b0 H
bx G
bx F
bx E
b0 D
b0 C
bx B
0A
0@
0?
b0 >
bx =
0<
bx ;
0:
bx 9
b0 8
b0 7
bx 6
bx 5
04
bx 3
02
01
bx 0
0/
bx .
0-
0,
bx +
0*
0)
bx (
0'
0&
b0 %
b100000000 $
1#
0"
b0 !
$end
#1000
b0 =
b0 J
b1 6
b1 K
b1 t
b0 F
b0 L
b0 O
b1 s
b0 v
b0 y
b0 .
b0 P
b0 |
b0 !"
b1010 $"
b0 ;
b0 E
b0 G
b0 9
b0 I
b0 N
b0 5
b0 Q
b0 u
b0 3
b0 x
b0 (
b0 '"
b0 0
b0 {
b0 %"
b0 B
b0 ~
b1010 +
b1010 #"
1"
#2000
0"
#3000
1"
#4000
0"
#5000
1"
#6000
0"
#7000
1"
#8000
0"
#9000
1"
#10000
0"
#11000
1"
0#
#12000
b1010 |
b1010 !
b1010 %
b1010 C
b1010 D
b1010 M
b1010 w
b1010 z
b1010 }
b1010 ""
b1010 &"
1*
1/
b10 8
b10 S
1n
b10000 7
b10000 R
1k
b10 s
b1 r
0"
#13000
b1010 0
b1010 {
b1010 %"
1"
#14000
b1011 $"
b0 !
b0 %
b0 C
b0 D
b0 M
b0 w
b0 z
b0 }
b0 ""
b0 &"
1'
1,
11
0*
0/
1p
1m
1j
b1 8
b1 S
0n
b100100 7
b100100 R
0k
b11 s
b10 r
0"
#15000
b1100 $"
b1011 +
b1011 #"
1"
#16000
b0 |
b1011 $"
12
1/
0'
0,
01
1i
1k
b100 8
b100 S
0p
0m
b10000 7
b10000 R
0j
b100 s
b11 r
0"
#17000
b0 0
b0 {
b0 %"
1"
#18000
1'
1?
02
0/
1p
1d
b1 8
b1 S
0i
b10000000000000 7
b10000000000000 R
0k
b1 s
b100 r
0"
#19000
1"
#20000
b1011 |
b1011 !
b1011 %
b1011 C
b1011 D
b1011 M
b1011 w
b1011 z
b1011 }
b1011 ""
b1011 &"
1*
1/
0'
0?
1n
1k
b10 8
b10 S
0p
b10000 7
b10000 R
0d
b10 s
b1 r
0"
#21000
b1011 !
b1011 %
b1011 C
b1011 D
b1011 M
b1011 w
b1011 z
b1011 }
b1011 ""
b1011 &"
b101100000000 (
b101100000000 '"
b1011 0
b1011 {
b1011 %"
1"
#22000
b1100 $"
b101100000000 y
b101100000000 !
b101100000000 %
b101100000000 C
b101100000000 D
b101100000000 M
b101100000000 w
b101100000000 z
b101100000000 }
b101100000000 ""
b101100000000 &"
1'
1,
11
0*
0/
1p
1m
1j
b1 8
b1 S
0n
b100100 7
b100100 R
0k
b11 s
b10 r
0"
#23000
b1 8
b1 S
1p
1m
b100100 7
b100100 R
1j
b1100 s
b1101 $"
b1011 .
b1011 P
b101100000000 !
b101100000000 %
b101100000000 C
b101100000000 D
b101100000000 M
b101100000000 w
b101100000000 z
b101100000000 }
b101100000000 ""
b101100000000 &"
b1100 +
b1100 #"
b101100000000 3
b101100000000 x
1"
#24000
b0 !
b0 %
b0 C
b0 D
b0 M
b0 w
b0 z
b0 }
b0 ""
b0 &"
b1100 $"
1@
1-
0'
0,
01
1c
1l
b10000 8
b10000 S
0p
0m
b1000 7
b1000 R
0j
b1 s
b1100 r
0"
#25000
1"
#26000
b1100 |
b1100 !
b1100 %
b1100 C
b1100 D
b1100 M
b1100 w
b1100 z
b1100 }
b1100 ""
b1100 &"
1*
1/
0@
0-
1n
1k
b10 8
b10 S
0c
b10000 7
b10000 R
0l
b10 s
b1 r
0"
#27000
b1100 !
b1100 %
b1100 C
b1100 D
b1100 M
b1100 w
b1100 z
b1100 }
b1100 ""
b1100 &"
b1000000001 (
b1000000001 '"
b1100 0
b1100 {
b1100 %"
1"
#28000
b1101 $"
b1000000001 y
b1000000001 !
b1000000001 %
b1000000001 C
b1000000001 D
b1000000001 M
b1000000001 w
b1000000001 z
b1000000001 }
b1000000001 ""
b1000000001 &"
1'
1,
11
0*
0/
1p
1m
1j
b1 8
b1 S
0n
b100100 7
b100100 R
0k
b1100 s
b10 r
0"
#29000
b1 8
b1 S
1p
1m
b100100 7
b100100 R
1j
b111 s
b10 .
b10 P
b1110 $"
b1000000001 !
b1000000001 %
b1000000001 C
b1000000001 D
b1000000001 M
b1000000001 w
b1000000001 z
b1000000001 }
b1000000001 ""
b1000000001 &"
b1000000001 3
b1000000001 x
b1101 +
b1101 #"
1"
#30000
b1 |
b1 !
b1 %
b1 C
b1 D
b1 M
b1 w
b1 z
b1 }
b1 ""
b1 &"
b1101 $"
12
1/
0'
0,
01
1i
1k
b100 8
b100 S
0p
0m
b10000 7
b10000 R
0j
b1000 s
b111 r
0"
#31000
b1 !
b1 %
b1 C
b1 D
b1 M
b1 w
b1 z
b1 }
b1 ""
b1 &"
b1 (
b1 '"
b1 0
b1 {
b1 %"
1"
#32000
b1 O
b1 !
b1 %
b1 C
b1 D
b1 M
b1 w
b1 z
b1 }
b1 ""
b1 &"
1:
1'
02
0/
1g
1p
b1 8
b1 S
0i
b10000000 7
b10000000 R
0k
b1001 s
b1000 r
0"
#33000
b1 !
b1 %
b1 C
b1 D
b1 M
b1 w
b1 z
b1 }
b1 ""
b1 &"
b1 =
b1 J
b0 6
b0 K
b0 t
b1 L
b1 9
b1 I
b1 N
1"
#34000
b1 F
b1 !
b1 %
b1 C
b1 D
b1 M
b1 w
b1 z
b1 }
b1 ""
b1 &"
14
1<
1?
0'
0:
1h
1f
1d
b1000 8
b1000 S
0p
b10000001000000 7
b10000001000000 R
0g
b1 s
b1001 r
0"
#35000
b10 F
b10 =
b10 J
b10 L
b10 !
b10 %
b10 C
b10 D
b10 M
b10 w
b10 z
b10 }
b10 ""
b10 &"
b1 ;
b1 E
b1 G
1"
#36000
b1101 |
b1101 !
b1101 %
b1101 C
b1101 D
b1101 M
b1101 w
b1101 z
b1101 }
b1101 ""
b1101 &"
b1 F
1*
1/
0<
04
0?
1n
1k
b10 8
b10 S
0f
0h
b10000 7
b10000 R
0d
b10 s
b1 r
0"
#37000
b1101 !
b1101 %
b1101 C
b1101 D
b1101 M
b1101 w
b1101 z
b1101 }
b1101 ""
b1101 &"
b100000010 (
b100000010 '"
b1101 0
b1101 {
b1101 %"
1"
#38000
b1110 $"
b100000010 y
b100000010 !
b100000010 %
b100000010 C
b100000010 D
b100000010 M
b100000010 w
b100000010 z
b100000010 }
b100000010 ""
b100000010 &"
1'
1,
11
0*
0/
1p
1m
1j
b1 8
b1 S
0n
b100100 7
b100100 R
0k
b111 s
b10 r
0"
#39000
b1 8
b1 S
1p
1m
b100100 7
b100100 R
1j
b101 s
b1111 $"
b1 .
b1 P
b100000010 !
b100000010 %
b100000010 C
b100000010 D
b100000010 M
b100000010 w
b100000010 z
b100000010 }
b100000010 ""
b100000010 &"
b1110 +
b1110 #"
b100000010 3
b100000010 x
1"
#40000
b10 |
b10 !
b10 %
b10 C
b10 D
b10 M
b10 w
b10 z
b10 }
b10 ""
b10 &"
b1110 $"
12
1/
0'
0,
01
1i
1k
b100 8
b100 S
0p
0m
b10000 7
b10000 R
0j
b110 s
b101 r
0"
#41000
b10 !
b10 %
b10 C
b10 D
b10 M
b10 w
b10 z
b10 }
b10 ""
b10 &"
b0 (
b0 '"
b10 0
b10 {
b10 %"
1"
#42000
b1 !
b1 %
b1 C
b1 D
b1 M
b1 w
b1 z
b1 }
b1 ""
b1 &"
1@
1&
02
0/
1c
1q
b10000 8
b10000 S
0i
b1 7
b1 R
0k
b1 s
b110 r
0"
#43000
b1 !
b1 %
b1 C
b1 D
b1 M
b1 w
b1 z
b1 }
b1 ""
b1 &"
b1 (
b1 '"
1"
#44000
b1110 |
b1110 !
b1110 %
b1110 C
b1110 D
b1110 M
b1110 w
b1110 z
b1110 }
b1110 ""
b1110 &"
1*
1/
0@
0&
1n
1k
b10 8
b10 S
0c
b10000 7
b10000 R
0q
b10 s
b1 r
0"
#45000
b1110 0
b1110 {
b1110 %"
1"
#46000
b1111 $"
b1 y
b1 !
b1 %
b1 C
b1 D
b1 M
b1 w
b1 z
b1 }
b1 ""
b1 &"
1'
1,
11
0*
0/
1p
1m
1j
b1 8
b1 S
0n
b100100 7
b100100 R
0k
b101 s
b10 r
0"
#47000
b1 8
b1 S
1p
1m
b100100 7
b100100 R
1j
b11 s
b10000 $"
b0 .
b0 P
b1 !
b1 %
b1 C
b1 D
b1 M
b1 w
b1 z
b1 }
b1 ""
b1 &"
b1111 +
b1111 #"
b1 3
b1 x
1"
#48000
b1 |
b1 !
b1 %
b1 C
b1 D
b1 M
b1 w
b1 z
b1 }
b1 ""
b1 &"
b1111 $"
12
1/
0'
0,
01
1i
1k
b100 8
b100 S
0p
0m
b10000 7
b10000 R
0j
b100 s
b11 r
0"
#49000
b1 0
b1 {
b1 %"
1"
#50000
b1 !
b1 %
b1 C
b1 D
b1 M
b1 w
b1 z
b1 }
b1 ""
b1 &"
1'
1?
02
0/
1p
1d
b1 8
b1 S
0i
b10000000000000 7
b10000000000000 R
0k
b1 s
b100 r
0"
#51000
1"
#52000
b1111 |
b1111 !
b1111 %
b1111 C
b1111 D
b1111 M
b1111 w
b1111 z
b1111 }
b1111 ""
b1111 &"
1*
1/
0'
0?
1n
1k
b10 8
b10 S
0p
b10000 7
b10000 R
0d
b10 s
b1 r
0"
#53000
b1111 !
b1111 %
b1111 C
b1111 D
b1111 M
b1111 w
b1111 z
b1111 }
b1111 ""
b1111 &"
b100000000 (
b100000000 '"
b1111 0
b1111 {
b1111 %"
1"
#54000
b10000 $"
b100000000 y
b100000000 !
b100000000 %
b100000000 C
b100000000 D
b100000000 M
b100000000 w
b100000000 z
b100000000 }
b100000000 ""
b100000000 &"
1'
1,
11
0*
0/
1p
1m
1j
b1 8
b1 S
0n
b100100 7
b100100 R
0k
b11 s
b10 r
0"
