RTL/design/modules/accumulator/accumulator.v
module accumulator(
    input clk,
    input rst,
    input acc_write,
    input acc_lower_write,
    input [15:0]bus,
    output reg [15:0]aout
);

reg [15:0]aout_nxt;


////////////// flops
always @(posedge clk ) begin
        if(rst)
            aout <= 0;
        else
            aout <= aout_nxt ;
end

///////////// comb
always @(*) begin
    if(acc_write)
        aout_nxt = bus;
    else if(acc_lower_write)
        aout_nxt = {8'b0,bus[7:0]};
    else
        aout_nxt = aout ;
end


endmodule

RTL/design/modules/accumulator/accumulator_tb.v
`timescale 1ns/1ps

module tb;

reg [15:0]bus;
reg clk,rst,acc_write,acc_lower_write;
wire [15:0] aout ;

accumulator dut(
    .clk(clk),
    .rst(rst),
    .acc_write(acc_write),
    .acc_lower_write(acc_lower_write),
    .bus(bus),
    .aout(aout)
);

always #5 clk = ~clk ; 

initial begin

{clk,rst,acc_write,acc_lower_write,bus} = 0;
$dumpfile("output.vcd");
$dumpvars(0,tb);

#100 $finish ; 

end

initial begin

    #12 ;
    rst = 1;

    #5;
    rst = 0;

    #2;
    bus = 16'd300;

    #3;
    acc_write = 1;

    #10;
    acc_write = 0;


    #5;
    rst = 1;

    #3;
    rst = 0;

    #3;
    bus = 16'b1101_1110_1101_1110;

    #2;
    acc_lower_write = 1;

    #13;
    acc_lower_write = 0;


end



endmodule

RTL/design/modules/accumulator/output.vcd
$date
	Fri Sep 26 19:21:20 2025
$end
$version
	Icarus Verilog
$end
$timescale
	1ps
$end
$scope module tb $end
$var wire 16 ! aout [15:0] $end
$var reg 1 " acc_lower_write $end
$var reg 1 # acc_write $end
$var reg 16 $ bus [15:0] $end
$var reg 1 % clk $end
$var reg 1 & rst $end
$scope module dut $end
$var wire 1 " acc_lower_write $end
$var wire 1 # acc_write $end
$var wire 16 ' bus [15:0] $end
$var wire 1 % clk $end
$var wire 1 & rst $end
$var reg 16 ( aout [15:0] $end
$var reg 16 ) aout_nxt [15:0] $end
$upscope $end
$upscope $end
$enddefinitions $end
$comment Show the parameter values. $end
$dumpall
$end
#0
$dumpvars
bx )
bx (
b0 '
0&
0%
b0 $
0#
0"
bx !
$end
#5000
1%
#10000
0%
#12000
1&
#15000
b0 )
b0 !
b0 (
1%
#17000
0&
#19000
b100101100 $
b100101100 '
#20000
0%
#22000
b100101100 )
1#
#25000
b100101100 !
b100101100 (
1%
#30000
0%
#32000
0#
#35000
1%
#37000
1&
#40000
0&
0%
#43000
b1101111011011110 $
b1101111011011110 '
#45000
b11011110 )
1"
1%
#50000
0%
#55000
b11011110 !
b11011110 (
1%
#58000
0"
