RTL/design/modules/output/out.v
module out(
    input clk,
    input rst,
    input [15:0]bus,
    input out_write,
    output reg[15:0]_out_
);

    reg [15:0] _out_nxt;

////////////// flops
always @(posedge clk) begin
        if(rst)
            _out_ <= 0;
        else
            _out_ <= _out_nxt ;
end

///////////// comb
always @(*) begin
    if(out_write)
        _out_nxt = bus;
    else
        _out_nxt = _out_ ;
end



endmodule

RTL/design/modules/output/out_tb.v
`timescale 1ns/1ps

module tb;

reg clk,rst,out_write;
reg [15:0]bus;
wire [15:0]_out_;

out dut(
    .clk(clk),
    .rst(rst),
    .out_write(out_write),
    .bus(bus),
    ._out_(_out_)
);

always #5 clk = ~clk ; 

initial begin
    {clk,rst,out_write,bus} = 0 ;
    $dumpfile("output.vcd");
    $dumpvars(0,tb);
    #100 $finish ; 
end

initial begin

#12;
rst  = 1;

#8 ;
rst = 0;

#1;
bus = 16'd74;

#2;
out_write = 1;

#5;
out_write = 0;


end

endmodule

RTL/design/modules/output/output.vcd
$date
	Fri Sep 26 22:35:01 2025
$end
$version
	Icarus Verilog
$end
$timescale
	1ps
$end
$scope module tb $end
$var wire 16 ! _out_ [15:0] $end
$var reg 16 " bus [15:0] $end
$var reg 1 # clk $end
$var reg 1 $ out_write $end
$var reg 1 % rst $end
$scope module dut $end
$var wire 16 & bus [15:0] $end
$var wire 1 # clk $end
$var wire 1 $ out_write $end
$var wire 1 % rst $end
$var reg 16 ' _out_ [15:0] $end
$var reg 16 ( _out_nxt [15:0] $end
$upscope $end
$upscope $end
$enddefinitions $end
$comment Show the parameter values. $end
$dumpall
$end
#0
$dumpvars
bx (
bx '
b0 &
0%
0$
0#
b0 "
bx !
$end
#5000
1#
#10000
0#
#12000
1%
#15000
b0 (
b0 !
b0 '
1#
#20000
0#
0%
#21000
b1001010 "
b1001010 &
#23000
b1001010 (
1$
#25000
b1001010 !
b1001010 '
1#
#28000
0$
