RTL/design/modules/mar/mar.v
module mar(
    input clk,
    input rst,
    input mar_write,
    input [15:0]bus,
    output reg [7:0]mar_out
);

reg [7:0]mar_out_nxt;


////////////// flops
always @(posedge clk) begin
        if(rst)
            mar_out <= 0;
        else
            mar_out <= mar_out_nxt ;
end

///////////// comb
always @(*) begin
    if(mar_write)
        mar_out_nxt = bus[7:0];
    else
        mar_out_nxt = mar_out ;
end


endmodule

RTL/design/modules/mar/mar_tb.v
`timescale 1ns/1ps

module tb;

reg [15:0]bus; 
reg clk,rst,mar_write;
wire [7:0]mar_out;

mar dut(
    .clk(clk),
    .rst(rst),
    .mar_write(mar_write),
    .bus(bus),
    .mar_out(mar_out)
);

always #5 clk = ~clk ; 

initial begin
    {clk,rst,mar_write,bus} = 0 ;
    $dumpfile("output.vcd");
    $dumpvars(0,tb);
    #100 $finish ; 

end

initial begin

#12;
rst  = 1;

#8 ;
rst = 0;

#1;
bus = 16'd74;

#2;
mar_write = 1;

#5;
mar_write = 0;


end
 
endmodule

RTL/design/modules/mar/output.vcd
$date
	Fri Sep 26 19:54:32 2025
$end
$version
	Icarus Verilog
$end
$timescale
	1ps
$end
$scope module tb $end
$var wire 8 ! mar_out [7:0] $end
$var reg 16 " bus [15:0] $end
$var reg 1 # clk $end
$var reg 1 $ mar_write $end
$var reg 1 % rst $end
$scope module dut $end
$var wire 16 & bus [15:0] $end
$var wire 1 # clk $end
$var wire 1 $ mar_write $end
$var wire 1 % rst $end
$var reg 8 ' mar_out [7:0] $end
$var reg 8 ( mar_out_nxt [7:0] $end
$upscope $end
$upscope $end
$enddefinitions $end
$comment Show the parameter values. $end
$dumpall
$end
#0
$dumpvars
bx (
bx '
b0 &
0%
0$
0#
b0 "
bx !
$end
#5000
1#
#10000
0#
#12000
1%
#15000
b0 (
b0 !
b0 '
1#
#20000
0#
0%
#21000
b1001010 "
b1001010 &
#23000
b1001010 (
1$
#25000
b1001010 !
b1001010 '
1#
#28000
0$
