RTL/design/modules/sap/b_register.v
module b_register(
    input clk,
    input rst,
    input b_write,
    input [15:0]bus,
    output reg [15:0]bout
);

reg [15:0]bout_nxt;


////////////// flops
always @(posedge clk ) begin
        if(rst)
            bout <= 0;
        else
            bout <= bout_nxt ;
end

///////////// comb
always @(*) begin
    if(b_write)
        bout_nxt = bus;
    else
        bout_nxt = bout ;
end


endmodule

RTL/design/modules/b_register/b_register_tb.v
`timescale 1ns/1ps

module tb;

    reg clk;
    reg rst;
    reg b_write;
    reg [15:0]bus;
    wire [15:0]bout;


    b_register dut(
        .clk(clk),
        .rst(rst),
        .b_write(b_write),
        .bus(bus),
        .bout(bout)
    );

always #5 clk = ~clk ; 

initial begin

{clk,rst,b_write,bus} = 0;
$dumpfile("output.vcd");
$dumpvars(0,tb);

#100 $finish ; 

end

initial begin

    #12;
    rst = 1;

    #7;
    rst = 0;

    #1;
    bus = 16'd400;
    
    #3;
    b_write = 1;

    #10;
    b_write = 0;

    #22;
    rst = 1;

    #4;
    rst = 0;

end


endmodule

RTL/design/modules/b_register/output.vcd
$date
	Fri Sep 26 19:35:55 2025
$end
$version
	Icarus Verilog
$end
$timescale
	1ps
$end
$scope module tb $end
$var wire 16 ! bout [15:0] $end
$var reg 1 " b_write $end
$var reg 16 # bus [15:0] $end
$var reg 1 $ clk $end
$var reg 1 % rst $end
$scope module dut $end
$var wire 1 " b_write $end
$var wire 16 & bus [15:0] $end
$var wire 1 $ clk $end
$var wire 1 % rst $end
$var reg 16 ' bout [15:0] $end
$var reg 16 ( bout_nxt [15:0] $end
$upscope $end
$upscope $end
$enddefinitions $end
$comment Show the parameter values. $end
$dumpall
$end
#0
$dumpvars
bx (
bx '
b0 &
0%
0$
b0 #
0"
bx !
$end
#5000
1$
#10000
0$
#12000
1%
#15000
b0 (
b0 !
b0 '
1$
#19000
0%
#20000
b110010000 #
b110010000 &
0$
#23000
b110010000 (
1"
#25000
b110010000 !
b110010000 '
1$
#30000
0$
#33000
0"
#35000
1$
#40000
0$
#45000
1$
#50000
0$
#55000
b0 (
b0 !
b0 '
1$
1%
#59000
0%
